pymodaq_plugins_physical_measurements/VERSION
pymodaq_plugins_physical_measurements/__init__.py
pymodaq_plugins_physical_measurements/daq_move_plugins/__init__.py
pymodaq_plugins_physical_measurements/daq_move_plugins/daq_move_Keithley2400.py
pymodaq_plugins_physical_measurements/daq_viewer_plugins/__init__.py
pymodaq_plugins_physical_measurements/daq_viewer_plugins/plugins_0D/__init__.py
pymodaq_plugins_physical_measurements/daq_viewer_plugins/plugins_0D/daq_0Dviewer_Keithley2110.py
pymodaq_plugins_physical_measurements/daq_viewer_plugins/plugins_0D/daq_0Dviewer_Keithley_Pico.py
pymodaq_plugins_physical_measurements/daq_viewer_plugins/plugins_0D/daq_0Dviewer_LockIn7270.py
pymodaq_plugins_physical_measurements/daq_viewer_plugins/plugins_0D/daq_0Dviewer_LockInSR830.py
pymodaq_plugins_physical_measurements/daq_viewer_plugins/plugins_1D/__init__.py
pymodaq_plugins_physical_measurements/daq_viewer_plugins/plugins_1D/daq_1Dviewer_LecroyWaverunner.py
pymodaq_plugins_physical_measurements/daq_viewer_plugins/plugins_1D/daq_1Dviewer_Picoscope.py
pymodaq_plugins_physical_measurements/daq_viewer_plugins/plugins_1D/daq_1Dviewer_Tektronix.py
pymodaq_plugins_physical_measurements/daq_viewer_plugins/plugins_2D/__init__.py
pymodaq_plugins_physical_measurements/daq_viewer_plugins/plugins_2D/daq_2Dviewer_GenICam.py
pymodaq_plugins_physical_measurements/daq_viewer_plugins/plugins_2D/daq_2Dviewer_OpenCVCam.py
pymodaq_plugins_physical_measurements/daq_viewer_plugins/plugins_2D/daq_2Dviewer_TIS.py
pymodaq_plugins_physical_measurements/daq_viewer_plugins/plugins_ND/__init__.py
pymodaq_plugins_physical_measurements/hardware/__init__.py
pymodaq_plugins_physical_measurements/hardware/TIS/TIS_UDSHL11.dll
pymodaq_plugins_physical_measurements/hardware/TIS/TIS_UDSHL11_x64.dll
pymodaq_plugins_physical_measurements/hardware/TIS/__init__.py
pymodaq_plugins_physical_measurements/hardware/TIS/index.chm
pymodaq_plugins_physical_measurements/hardware/TIS/tisgrabber.dll
pymodaq_plugins_physical_measurements-0.1.1.dist-info/LICENSE
pymodaq_plugins_physical_measurements-0.1.1.dist-info/METADATA
pymodaq_plugins_physical_measurements-0.1.1.dist-info/WHEEL
pymodaq_plugins_physical_measurements-0.1.1.dist-info/entry_points.txt
pymodaq_plugins_physical_measurements-0.1.1.dist-info/top_level.txt
pymodaq_plugins_physical_measurements-0.1.1.dist-info/RECORD
